WORC/WORC.py
WORC/__init__.py
WORC/addexceptions.py
WORC/index.rst
WORC/IOparser/__init__.py
WORC/IOparser/config_WORC.py
WORC/IOparser/config_io_PyRadiomics.py
WORC/IOparser/config_io_classifier.py
WORC/IOparser/config_io_combat.py
WORC/IOparser/config_preprocessing.py
WORC/IOparser/config_segmentix.py
WORC/IOparser/file_io.py
WORC/classification/AdvancedSampler.py
WORC/classification/ObjectSampler.py
WORC/classification/SearchCV.py
WORC/classification/__init__.py
WORC/classification/construct_classifier.py
WORC/classification/createfixedsplits.py
WORC/classification/crossval.py
WORC/classification/fitandscore.py
WORC/classification/metrics.py
WORC/classification/parameter_optimization.py
WORC/classification/regressors.py
WORC/classification/smac.py
WORC/classification/trainclassifier.py
WORC/classification/utils.py
WORC/detectors/__init__.py
WORC/detectors/detectors.py
WORC/doc/Makefile
WORC/doc/README
WORC/doc/__placeholder__
WORC/doc/conf.py
WORC/doc/doc_clean.py
WORC/doc/doc_generate.py
WORC/doc/generate_config.py
WORC/doc/generate_modules.py
WORC/doc/index.rst
WORC/doc/index.template
WORC/doc/make.bat
WORC/doc/requirements-pre-numpy.txt
WORC/doc/requirements.txt
WORC/doc/_build/doctrees/WORC.config.doctree
WORC/doc/_build/doctrees/environment.pickle
WORC/doc/_build/doctrees/index.doctree
WORC/doc/_build/doctrees/autogen/WORC.IOparser.doctree
WORC/doc/_build/doctrees/autogen/WORC.classification.doctree
WORC/doc/_build/doctrees/autogen/WORC.config.doctree
WORC/doc/_build/doctrees/autogen/WORC.detectors.doctree
WORC/doc/_build/doctrees/autogen/WORC.doctree
WORC/doc/_build/doctrees/autogen/WORC.exampledata.doctree
WORC/doc/_build/doctrees/autogen/WORC.export.doctree
WORC/doc/_build/doctrees/autogen/WORC.facade.doctree
WORC/doc/_build/doctrees/autogen/WORC.facade.helpers.doctree
WORC/doc/_build/doctrees/autogen/WORC.facade.intermediatefacade.doctree
WORC/doc/_build/doctrees/autogen/WORC.fastrconfig.doctree
worc-3.7.0.dist-info/licenses/LICENSE
worc-3.7.0.dist-info/METADATA
worc-3.7.0.dist-info/WHEEL
worc-3.7.0.dist-info/entry_points.txt
worc-3.7.0.dist-info/top_level.txt
worc-3.7.0.dist-info/RECORD
