Metadata-Version: 2.4
Name: WORC
Version: 3.7.0
Summary: Workflow for Optimal Radiomics Classification.
Author-email: "Martijn P. A. Starmans" <m.starmans@erasmusmc.nl>
License-Expression: Apache-2.0
Keywords: bioinformatics,radiomics,features
Classifier: Development Status :: 5 - Production/Stable
Classifier: Intended Audience :: Developers
Classifier: Intended Audience :: Science/Research
Classifier: Intended Audience :: Healthcare Industry
Classifier: Intended Audience :: Information Technology
Classifier: Intended Audience :: Education
Classifier: Natural Language :: English
Classifier: Operating System :: OS Independent
Classifier: Programming Language :: Python :: 3.11
Classifier: Programming Language :: Python :: 3 :: Only
Classifier: Topic :: Scientific/Engineering :: Information Analysis
Classifier: Topic :: System :: Distributed Computing
Classifier: Topic :: System :: Logging
Classifier: Topic :: Utilities
Requires-Python: >=3.11
License-File: LICENSE
Requires-Dist: fastr
Requires-Dist: imbalanced-learn
Requires-Dist: lifelines
Requires-Dist: lxml
Requires-Dist: matplotlib
Requires-Dist: matplot2tikz
Requires-Dist: natsort
Requires-Dist: networkx<=3.4.2
Requires-Dist: numpy<=1.26.3
Requires-Dist: pandas
Requires-Dist: pyradiomics==3.0.1
Requires-Dist: PREDICT>=3.2.0
Requires-Dist: pyOpenSSL
Requires-Dist: pydicom
Requires-Dist: rdflib
Requires-Dist: scikit-image
Requires-Dist: scikit-learn
Requires-Dist: scipy
Requires-Dist: setuptools<=80.8.0
Requires-Dist: SimpleITK
Requires-Dist: six
Requires-Dist: sphinx
Requires-Dist: tables
Requires-Dist: tqdm
Requires-Dist: xgboost
Requires-Dist: xlrd
Requires-Dist: xnat
Provides-Extra: test
Requires-Dist: nose; extra == "test"
Requires-Dist: coverage; extra == "test"
Provides-Extra: dev
Requires-Dist: pytest; extra == "dev"
Requires-Dist: black; extra == "dev"
Requires-Dist: flake8; extra == "dev"
Requires-Dist: pre-commit; extra == "dev"
Provides-Extra: docs
Requires-Dist: sphinx; extra == "docs"
Requires-Dist: sphinx_rtd_theme; extra == "docs"
Requires-Dist: numpydoc; extra == "docs"
Requires-Dist: sphinx-autodoc-typehints; extra == "docs"
Requires-Dist: readthedocs-sphinx-search; extra == "docs"
Requires-Dist: sphinx-argparse; extra == "docs"
Requires-Dist: sphinxcontrib-httpdomain; extra == "docs"
Requires-Dist: sphinx-autodoc-typehints; extra == "docs"
Dynamic: license-file
